minimono/API/__init__.py
minimono/API/api_call.py
minimono/API/client.py
minimono/__init__.py
minimono/abstract/__init__.py
minimono/abstract/caller_elements.py
minimono/models/__init__.py
minimono/models/enumerators.py
minimono/models/models.py
minimono/models/utility.py
minimono/py.typed
minimono-0.4.0.dist-info/LICENSE
minimono-0.4.0.dist-info/WHEEL
minimono-0.4.0.dist-info/METADATA
minimono-0.4.0.dist-info/RECORD
