Metadata-Version: 2.1
Name: minimono
Version: 0.4.0
Summary: A wrapper for monobanks API. With caching and serialization.
License: MIT
Author: Arthur Ryzhak
Author-email: ryzhakar@gmail.com
Requires-Python: >=3.8,<4.0
Classifier: License :: OSI Approved :: MIT License
Classifier: Programming Language :: Python :: 3
Classifier: Programming Language :: Python :: 3.10
Classifier: Programming Language :: Python :: 3.8
Classifier: Programming Language :: Python :: 3.9
Requires-Dist: pydantic (>=1.10.1,<2.0.0)
Requires-Dist: requests (>=2.28.1,<3.0.0)
